graphene_django_framework/__init__.py
graphene_django_framework/converter.py
graphene_django_framework/decorators.py
graphene_django_framework/exceptions.py
graphene_django_framework/fields.py
graphene_django_framework/mixins.py
graphene_django_framework/models.py
graphene_django_framework/paginator.py
graphene_django_framework/sites.py
graphene_django_framework/types.py
graphene_django_framework/utils.py
graphene_django_framework-0.7.1.dist-info/LICENSE
graphene_django_framework-0.7.1.dist-info/METADATA
graphene_django_framework-0.7.1.dist-info/WHEEL
graphene_django_framework-0.7.1.dist-info/top_level.txt
graphene_django_framework-0.7.1.dist-info/RECORD
